nbtemplate
