Metadata-Version: 1.1
Name: nbtemplate
Version: 0.0.1
Summary: Render iPython notebooks to other layouts, via templates. Library and command-line tool.
Home-page: http://github.com/jsvine/nbtemplate/
Author: Jeremy Singer-Vine
Author-email: jsvine@gmail.com
License: MIT
Keywords: ipython notebooks nbconvert
Platform: UNKNOWN
Classifier: Development Status :: 3 - Alpha
Classifier: Intended Audience :: Developers
Classifier: License :: OSI Approved :: MIT License
Classifier: Operating System :: OS Independent
Classifier: Programming Language :: Python :: 2.6
Classifier: Programming Language :: Python :: 2.7
Classifier: Programming Language :: Python :: 3.3
